[
  {
    "id": "rec0L1z8pdDLW8VBr",
    "title": "Directions",
    "creator": "they can talk",
    "url": "https://64.media.tumblr.com/82577cfcc82cf712dae4523058dc1ea2/tumblr_p2kqpxmSYn1uacv0ho1_540.jpg",
    "tags": [
      "animals"
    ]
  },
  {
    "id": "rec2FGQbNrTSMgQbz",
    "title": "Anxious",
    "creator": "The Other End",
    "url": "https://i1.wp.com/www.kohney.com/wp-content/uploads/2020/01/site-jan-20-sweaty.jpg",
    "tags": [
      "psychology"
    ]
  },
  {
    "id": "rec4HnVL8NW4oFrex",
    "title": "This Is Why You Shouldn't Interrupt A Programmer",
    "creator": "The Slightly Disgruntled Scientist",
    "url": "https://heeris.id.au/trinkets/ProgrammerInterrupted.png",
    "tags": [
      "development",
      "productivity"
    ]
  },
  {
    "id": "rec7bd9xBtA2sO59r",
    "title": "Bully",
    "creator": "Saturday Morning Breakfast Cereal",
    "url": "https://www.smbc-comics.com/comics/1521555077-20180320.png",
    "tags": [
      "relationships"
    ]
  },
  {
    "id": "rec8vX2HbCvsXeFcj",
    "title": "The Real Villain",
    "creator": "Saturday Morning Breakfast Cereal",
    "url": "https://www.smbc-comics.com/comics/1548856040-20190130.png",
    "tags": [
      "crime"
    ]
  },
  {
    "id": "rec9yvsgi5YhUOgsO",
    "title": "Relationships: A Guide",
    "creator": "Saturday Morning Breakfast Cereal",
    "url": "https://www.smbc-comics.com/comics/20101103.gif",
    "tags": [
      "relationships"
    ]
  },
  {
    "id": "recB1ds7lvx93bsxE",
    "title": "Cocktail Party",
    "creator": "The Other End",
    "url": "https://i0.wp.com/www.kohney.com/wp-content/uploads/2021/09/aug30-and-early-something-else-2021-scaled.jpg",
    "tags": [
      "relationships"
    ]
  },
  {
    "id": "recB7C9AU0aza9RCD",
    "title": "No\\, The Other One",
    "creator": "xkcd",
    "url": "https://imgs.xkcd.com/comics/no_the_other_one_2x.png",
    "tags": [
      "geography"
    ]
  },
  {
    "id": "recBRtBTZGYGnmCc0",
    "title": "Self-Isolate",
    "creator": "xkcd",
    "url": "https://imgs.xkcd.com/comics/self_isolate.png",
    "tags": [
      "health",
      "life"
    ]
  },
  {
    "id": "recBmHaFUgofF6pLK",
    "title": "Screen Time",
    "creator": "Saturday Morning Breakfast Cereal",
    "url": "https://www.smbc-comics.com/comics/1548080776-20190121.png",
    "tags": [
      "health",
      "technology"
    ]
  },
  {
    "id": "recCL08mEMLFkk1O9",
    "title": "Hubris",
    "creator": "Saturday Morning Breakfast Cereal",
    "url": "https://www.smbc-comics.com/comics/1516896042-20180125.png",
    "tags": [
      "animals"
    ]
  },
  {
    "id": "recDBnBniHQmOX68h",
    "title": "A Bunch of Rocks",
    "creator": "xkcd",
    "url": "https://imgs.xkcd.com/comics/a_bunch_of_rocks.png",
    "tags": [
      "astronomy"
    ]
  },
  {
    "id": "recDSJtcOHIIie0AS",
    "title": "Bears Gone Camping",
    "creator": "The Other End",
    "url": "https://i1.wp.com/www.kohney.com/wp-content/uploads/2018/06/6-3-Bears-Gone-Camping.jpg",
    "tags": [
      "animals"
    ]
  },
  {
    "id": "recEJftc1NtndolGM",
    "title": "HTTP Status Codes",
    "creator": "MonkeyUser",
    "url": "https://www.monkeyuser.com/assets/images/2017/23-http-status-codes.png",
    "tags": [
      "development"
    ]
  },
  {
    "id": "recEjoMu0rWHnWw0C",
    "title": "The Event",
    "creator": "Saturday Morning Breakfast Cereal",
    "url": "https://www.smbc-comics.com/comics/1533740028-20180814.png",
    "tags": [
      "fear",
      "work"
    ]
  },
  {
    "id": "recFmDuGcpsNUvsj2",
    "title": "Know",
    "creator": "Poorly Drawn Lines",
    "url": "https://poorlydrawnlines.com/wp-content/uploads/2018/02/know.png",
    "tags": [
      "knowledge"
    ]
  },
  {
    "id": "recGKS4YHQ0rMpBVR",
    "title": "Report",
    "creator": "Poorly Drawn Lines",
    "url": "https://poorlydrawnlines.com/wp-content/uploads/2018/05/report.png",
    "tags": [
      "astronomy",
      "engineering"
    ]
  },
  {
    "id": "recGKUq9CjiJJGv9s",
    "title": "Everytime",
    "creator": "MonkeyUser",
    "url": "https://www.monkeyuser.com/assets/images/2018/84-everytime.png",
    "tags": [
      "development"
    ]
  },
  {
    "id": "recGNvEBDH9Y2x3Zg",
    "title": "Solar System Changes",
    "creator": "xkcd",
    "url": "https://imgs.xkcd.com/comics/solar_system_changes_2x.png",
    "tags": [
      "astronomy"
    ]
  },
  {
    "id": "recGaqVO2NbTSZIsX",
    "title": "Thin Ice",
    "creator": "Saturday Morning Breakfast Cereal",
    "url": "https://www.smbc-comics.com/comics/1558443793-20190521.png",
    "tags": [
      "climate"
    ]
  },
  {
    "id": "recGeP5vatu3bYHIF",
    "title": "How to eat a burrito",
    "creator": "The Oatmeal",
    "url": "https://s3.amazonaws.com/theoatmeal-img/comics/how_eat_burrito/how_eat_burrito.png",
    "tags": [
      "food"
    ]
  },
  {
    "id": "recGgHf8f8mUWSxdx",
    "title": "Tasks",
    "creator": "xkcd",
    "url": "https://imgs.xkcd.com/comics/tasks_2x.png",
    "tags": [
      "productivity"
    ]
  },
  {
    "id": "recH25W4SscBNg6Vg",
    "title": "Star Wars Fan Theories",
    "creator": "The Other End",
    "url": "https://i1.wp.com/www.kohney.com/wp-content/uploads/2022/01/site-star-wars-fan-theories-jan-4-2022-scaled.jpg",
    "tags": [
      "film"
    ]
  },
  {
    "id": "recH5gHNbTAQQUJNg",
    "title": "The BDLPSWDKS Effect",
    "creator": "xkcd",
    "url": "https://imgs.xkcd.com/comics/the_bdlpswdks_effect_2x.png",
    "tags": [
      "science"
    ]
  },
  {
    "id": "recHKIYeYn1eQGETT",
    "title": "Who put me in here?",
    "creator": "Port Sherry",
    "url": "http://portsherry.com/wp-content/uploads/2020/07/SHERR737.png",
    "tags": [
      "life"
    ]
  },
  {
    "id": "recIhFoS2kw4K7T4j",
    "title": "Fossils",
    "creator": "Saturday Morning Breakfast Cereal",
    "url": "https://www.smbc-comics.com/comics/1517325219-soonish30.png",
    "tags": [
      "religion"
    ]
  },
  {
    "id": "recIjkwnubXX91E7H",
    "title": "Trap I",
    "creator": "Poorly Drawn Lines",
    "url": "https://poorlydrawnlines.com/wp-content/uploads/2018/02/trap.png",
    "tags": [
      "animals"
    ]
  },
  {
    "id": "recJFCtzqqKU6XKSF",
    "title": "Trap II: Mouse Problems",
    "creator": "Poorly Drawn Lines",
    "url": "https://poorlydrawnlines.com/wp-content/uploads/2018/02/trap-ii-mouse-problems.png",
    "tags": [
      "animals"
    ]
  },
  {
    "id": "recK9S2l9N8ld1Uya",
    "title": "npm Delivery",
    "creator": "MonkeyUser",
    "url": "https://www.monkeyuser.com/assets/images/2017/52-npm-delivery.png",
    "tags": [
      "development"
    ]
  },
  {
    "id": "recKRJ5FUVrsAtRXT",
    "title": "Unfinished Work",
    "creator": "MonkeyUser",
    "url": "https://www.monkeyuser.com/assets/images/2018/95-unfinished-work.png",
    "tags": [
      "development"
    ]
  },
  {
    "id": "recKwVVU62SrCK5n5",
    "title": "Happy Easter",
    "creator": "The Other End",
    "url": "https://i1.wp.com/www.kohney.com/wp-content/uploads/2018/04/4-1-Happy-Easter.jpg",
    "tags": [
      "religion"
    ]
  },
  {
    "id": "recLm7ca5eYfI8eq7",
    "title": "The Truth",
    "creator": "Saturday Morning Breakfast Cereal",
    "url": "https://www.smbc-comics.com/comics/1519052775-20180219.png",
    "tags": [
      "family"
    ]
  },
  {
    "id": "recN6cL5fFbfbonFT",
    "title": "Time Stop",
    "creator": "Saturday Morning Breakfast Cereal",
    "url": "https://www.smbc-comics.com/comics/1620750456-20210511.png",
    "tags": [
      "time"
    ]
  },
  {
    "id": "recNOfAQuuBc4IK6v",
    "title": "COVID Risk Comfort Zone",
    "creator": "xkcd",
    "url": "https://imgs.xkcd.com/comics/covid_risk_comfort_zone_2x.png",
    "tags": [
      "health"
    ]
  },
  {
    "id": "recNkCJR7CyVXB7Og",
    "title": "Pull Request",
    "creator": "MonkeyUser",
    "url": "https://www.monkeyuser.com/assets/images/2018/99-pull-request.png",
    "tags": [
      "development"
    ]
  },
  {
    "id": "recNnBmJfqR7Oz5G9",
    "title": "The End",
    "creator": "Saturday Morning Breakfast Cereal",
    "url": "https://www.smbc-comics.com/comics/1624361675-20210622.png",
    "tags": [
      "productivity"
    ]
  },
  {
    "id": "recNw4WED3rbBIifN",
    "title": "Seem Tired",
    "creator": "Poorly Drawn Lines",
    "url": "https://poorlydrawnlines.com/wp-content/uploads/2021/06/seem-tired-1.png",
    "tags": [
      "life"
    ]
  },
  {
    "id": "recNwIrIOpaXSBXqQ",
    "title": "Quantum Bits",
    "creator": "Saturday Morning Breakfast Cereal",
    "url": "https://www.smbc-comics.com/comics/1527429710-20180527.png",
    "tags": [
      "astronomy"
    ]
  },
  {
    "id": "recOIvgwCuXLFtJIE",
    "title": "Backpack Decisions",
    "creator": "xkcd",
    "url": "https://imgs.xkcd.com/comics/backpack_decisions_2x.png",
    "tags": [
      "travel",
      "productivity"
    ]
  },
  {
    "id": "recOcdj4VKDCaAgEZ",
    "title": "Tech Support",
    "creator": "xkcd",
    "url": "https://imgs.xkcd.com/comics/tech_support.png",
    "tags": [
      "development",
      "technology"
    ]
  },
  {
    "id": "recOsuc85QPFVFTnT",
    "title": "Lisp",
    "creator": "xkcd",
    "url": "https://imgs.xkcd.com/comics/lisp.jpg",
    "tags": [
      "development"
    ]
  },
  {
    "id": "recQzWMMxaBKAqYOT",
    "title": "Worst Thing That Could Happen",
    "creator": "xkcd",
    "url": "https://imgs.xkcd.com/comics/worst_thing_that_could_happen_2x.png",
    "tags": [
      "paranoia"
    ]
  },
  {
    "id": "recQzy2sR7XcDHLsV",
    "title": "AGI",
    "creator": "Saturday Morning Breakfast Cereal",
    "url": "https://www.smbc-comics.com/comics/1618403670-20210414.png",
    "tags": [
      "ai",
      "race"
    ]
  },
  {
    "id": "recRWiBtOrbiQFxmX",
    "title": "Mustard",
    "creator": "The Other End",
    "url": "https://i2.wp.com/www.kohney.com/wp-content/uploads/2021/11/upsetting-joke-1.jpg",
    "tags": [
      "food",
      "sex"
    ]
  },
  {
    "id": "recS2bYlMB2pr5Ygx",
    "title": "Instagram",
    "creator": "xkcd",
    "url": "https://imgs.xkcd.com/comics/instagram_2x.png",
    "tags": [
      "social"
    ]
  },
  {
    "id": "recSWAbdrX0V0kHQt",
    "title": "Everything Bagel",
    "creator": "The Other End",
    "url": "https://i2.wp.com/www.kohney.com/wp-content/uploads/2018/10/SITE-Everything-Bagel.jpg",
    "tags": [
      "food",
      "fantasy"
    ]
  },
  {
    "id": "recSc3gBqF4xCi1tq",
    "title": "Stone Cold",
    "creator": "Poorly Drawn Lines",
    "url": "https://poorlydrawnlines.com/wp-content/uploads/2018/01/stone-cold.png",
    "tags": [
      "relationships"
    ]
  },
  {
    "id": "recSpO1NERI5rv0Cj",
    "title": "Footprints and Photos",
    "creator": "The Other End",
    "url": "https://i2.wp.com/www.kohney.com/wp-content/uploads/2018/08/8-8-Footprints.jpg",
    "tags": [
      "animals"
    ]
  },
  {
    "id": "recT9dtzoAF7PAzcT",
    "title": "Man vs Nature",
    "creator": "The Other End",
    "url": "https://i0.wp.com/www.kohney.com/wp-content/uploads/2018/05/5-24-Man-v-Nature.jpg",
    "tags": [
      "animals",
      "ecology"
    ]
  },
  {
    "id": "recTaD13xGt6CykaL",
    "title": "Start",
    "creator": "Saturday Morning Breakfast Cereal",
    "url": "https://www.smbc-comics.com/comics/1617552070-20210404.png",
    "tags": [
      "religion"
    ]
  },
  {
    "id": "recTn9miqCcmzxoqn",
    "title": "Wisdom of the Ancients",
    "creator": "xkcd",
    "url": "https://imgs.xkcd.com/comics/wisdom_of_the_ancients.png",
    "tags": [
      "development",
      "knowledge"
    ]
  },
  {
    "id": "recU9CYybBLkg7Lgy",
    "title": "Perspective",
    "creator": "xkcd",
    "url": "https://imgs.xkcd.com/comics/perspective.png",
    "tags": [
      "technology"
    ]
  },
  {
    "id": "recUJWuYY7o14lgCG",
    "title": "Software Development",
    "creator": "xkcd",
    "url": "https://imgs.xkcd.com/comics/software_development_2x.png",
    "tags": [
      "development"
    ]
  },
  {
    "id": "recUd02CtdKpp1QeK",
    "title": "Open Source Issues",
    "creator": "MonkeyUser",
    "url": "https://www.monkeyuser.com/assets/images/2017/48-open-source-issues.png",
    "tags": [
      "development"
    ]
  },
  {
    "id": "recUuOmIx4l7XXn1A",
    "title": "COVID Risk Chart",
    "creator": "xkcd",
    "url": "https://imgs.xkcd.com/comics/covid_risk_chart_2x.png",
    "tags": [
      "health"
    ]
  },
  {
    "id": "recWpwQ6jKIhZ2WFk",
    "title": "Plucked Up",
    "creator": "Loading Artist",
    "url": "https://loadingartist.com/comic/plucked-up-1/plucked-up-1_hua7c636839a0cf7457e37af5189afce54_1856283_800x0_resize_q85_h2_lanczos_2.webp",
    "tags": [
      "work"
    ]
  },
  {
    "id": "recY3cmZgXiPS9tnY",
    "title": "Potential",
    "creator": "Saturday Morning Breakfast Cereal",
    "url": "https://www.smbc-comics.com/comics/1523907270-soonish36.png",
    "tags": [
      "family",
      "life"
    ]
  },
  {
    "id": "recYouKoHxyEeBDKF",
    "title": "Unsubscribe Message",
    "creator": "xkcd",
    "url": "https://imgs.xkcd.com/comics/unsubscribe_message_2x.png",
    "tags": [
      "advertising"
    ]
  },
  {
    "id": "recZZS4vWj6DaDC3V",
    "title": "Automation",
    "creator": "xkcd",
    "url": "https://imgs.xkcd.com/comics/automation_2x.png",
    "tags": [
      "engineering"
    ]
  },
  {
    "id": "recZqhjz4qP4Xy3TW",
    "title": "Come Back",
    "creator": "Saturday Morning Breakfast Cereal",
    "url": "https://www.smbc-comics.com/comics/1597070857-20200810.png",
    "tags": [
      "knowledge",
      "finance"
    ]
  },
  {
    "id": "recZzyxTCeioG26kP",
    "title": "Starwatching",
    "creator": "xkcd",
    "url": "https://imgs.xkcd.com/comics/starwatching.png",
    "tags": [
      "astronomy"
    ]
  },
  {
    "id": "reca1cWh606bcv5lv",
    "title": "Platypus",
    "creator": "Saturday Morning Breakfast Cereal",
    "url": "https://www.smbc-comics.com/comics/1525015322-20180429.png",
    "tags": [
      "animals",
      "religion"
    ]
  },
  {
    "id": "recaFYTRvW6fhO6qZ",
    "title": "Talk to me",
    "creator": "Commitstrip ",
    "url": "https://www.commitstrip.com/wp-content/uploads/2020/07/Strip-Serveur-muet-650-finalenglish.jpg",
    "tags": [
      "development"
    ]
  },
  {
    "id": "recam27TCehK63PkH",
    "title": "Clear Message",
    "creator": "The Perry Bible Fellowship",
    "url": "https://pbfcomics.com/wp-content/uploads/2021/04/PBF-Clear_Message.png",
    "tags": [
      "animals"
    ]
  },
  {
    "id": "recatv7kviyz0JWB7",
    "title": "Reference",
    "creator": "Saturday Morning Breakfast Cereal",
    "url": "https://www.smbc-comics.com/comics/1617287785-20210401.png",
    "tags": [
      "science",
      "social"
    ]
  },
  {
    "id": "recc6igZRMZHnAzbY",
    "title": "Mysterious Key of Mystery",
    "creator": "The Other End",
    "url": "https://i1.wp.com/www.kohney.com/wp-content/uploads/2021/03/march1-cancel-jim-scaled.jpg",
    "tags": [
      "film",
      "mystery",
      "tv"
    ]
  },
  {
    "id": "reccZFDOuaIV1osTu",
    "title": "Balls",
    "creator": "Things in Squares",
    "url": "https://www.thingsinsquares.com/wp-content/uploads/balls-comic.png",
    "tags": [
      "sports"
    ]
  },
  {
    "id": "recdQbf7ghXIxPVeC",
    "title": "Great Grandpa",
    "creator": "The Other End",
    "url": "https://i0.wp.com/www.kohney.com/wp-content/uploads/2022/02/site-great-grandfather-february-2022-scaled.jpg",
    "tags": [
      "family"
    ]
  },
  {
    "id": "recei4AbjXbyMqZT2",
    "title": "Hole",
    "creator": "Poorly Drawn Lines",
    "url": "https://poorlydrawnlines.com/wp-content/uploads/2018/04/hole.png",
    "tags": [
      "finance"
    ]
  },
  {
    "id": "recfo7zOCjfTGNIed",
    "title": "Hard Work",
    "creator": "Extra Fabulos",
    "url": "https://extrafabulouscomics.com/wp-content/uploads/2018/04/7-1-e1525093123484.jpg",
    "tags": [
      "animals"
    ]
  },
  {
    "id": "recfqujxQCNHUzuRJ",
    "title": "Duty Calls",
    "creator": "xkcd",
    "url": "https://imgs.xkcd.com/comics/duty_calls.png",
    "tags": [
      "social"
    ]
  },
  {
    "id": "recft9jVIjfEn4Twm",
    "title": "Making Progress",
    "creator": "xkcd",
    "url": "https://imgs.xkcd.com/comics/making_progress_2x.png",
    "tags": [
      "productivity"
    ]
  },
  {
    "id": "recgBsPO2ccI2y0yb",
    "title": "Cobol Programmer",
    "creator": "Dilbert",
    "url": "https://assets.amuniversal.com/cbf69860a084012f2fe600163e41dd5b",
    "tags": [
      "development"
    ]
  },
  {
    "id": "rechBofRmhePR45wB",
    "title": "Debugging",
    "creator": "MonkeyUser",
    "url": "https://www.monkeyuser.com/assets/images/2018/76-debugging.png",
    "tags": [
      "development"
    ]
  },
  {
    "id": "reciPEEhdfO1yafFI",
    "title": "Voting Software",
    "creator": "xkcd",
    "url": "https://imgs.xkcd.com/comics/voting_software_2x.png",
    "tags": [
      "politics",
      "technology"
    ]
  },
  {
    "id": "reckn4DY9K1H533CK",
    "title": "Ballmer Peak",
    "creator": "xkcd",
    "url": "https://imgs.xkcd.com/comics/ballmer_peak.png",
    "tags": [
      "engineering"
    ]
  },
  {
    "id": "reckoOC3TEmHr8Dq1",
    "title": "Voynich Manuscript",
    "creator": "xkcd",
    "url": "https://imgs.xkcd.com/comics/voynich_manuscript.png",
    "tags": [
      "history",
      "literature"
    ]
  },
  {
    "id": "reckxxOzwpSVlP5iW",
    "title": "Smaug",
    "creator": "Saturday Morning Breakfast Cereal",
    "url": "https://www.smbc-comics.com/comics/1526046792-20180511.png",
    "tags": [
      "finance",
      "fantasy"
    ]
  },
  {
    "id": "recljZ1uQPHIAuFhI",
    "title": "It haunts us",
    "creator": "CommitStrip",
    "url": "https://www.commitstrip.com/wp-content/uploads/2021/06/Strip-Refractoring-du-code-650-finalenglish.jpg",
    "tags": [
      "development"
    ]
  },
  {
    "id": "recm1b8zwGh2wBVu0",
    "title": "Relationship Goals",
    "creator": "The Other End",
    "url": "https://i1.wp.com/www.kohney.com/wp-content/uploads/2021/03/site-march26-st-louis-has-lots-of-free-attractions.jpg",
    "tags": [
      "relationships",
      "crime"
    ]
  },
  {
    "id": "recmUwtO011zty3W6",
    "title": "Simpler Times",
    "creator": "Poorly Drawn Lines",
    "url": "https://poorlydrawnlines.com/wp-content/uploads/2017/11/simpler-times.png",
    "tags": [
      "community"
    ]
  },
  {
    "id": "recodx569PppUzFjZ",
    "title": "Judge",
    "creator": "they can talk",
    "url": "https://64.media.tumblr.com/a9373fa3bb80a6cb4a1478efdd1ef249/tumblr_p74ig1jDs61uacv0ho1_540.jpg",
    "tags": [
      "animals"
    ]
  },
  {
    "id": "recophIZTdNaBTyVP",
    "title": "Password Strength",
    "creator": "xkcd",
    "url": "https://imgs.xkcd.com/comics/password_strength.png",
    "tags": [
      "security",
      "privacy"
    ]
  },
  {
    "id": "recprD7ZaqOTQD0Tk",
    "title": "Ten Thousand",
    "creator": "xkcd",
    "url": "https://imgs.xkcd.com/comics/ten_thousand_2x.png",
    "tags": [
      "knowledge"
    ]
  },
  {
    "id": "recqxDfBLLOe7zkJx",
    "title": "Cold",
    "creator": "xkcd",
    "url": "https://imgs.xkcd.com/comics/cold_2x.png",
    "tags": [
      "climate"
    ]
  },
  {
    "id": "recqy6wt0x88CoMXZ",
    "title": "Origin Story",
    "creator": "Port Sherry",
    "url": "http://portsherry.com/wp-content/uploads/2015/08/2015-08-06-sherry404REV.png",
    "tags": [
      "family"
    ]
  },
  {
    "id": "recrcxu8Djs0dxUQm",
    "title": "Need",
    "creator": "Saturday Morning Breakfast Cereal",
    "url": "https://www.smbc-comics.com/comics/1619091312-20210422.png",
    "tags": [
      "finance",
      "life"
    ]
  },
  {
    "id": "recsC2eDMFl26tVBM",
    "title": "Space Poop",
    "creator": "Saturday Morning Breakfast Cereal",
    "url": "https://www.smbc-comics.com/comics/1544451490-20181210.png",
    "tags": [
      "astronomy",
      "engineering"
    ]
  },
  {
    "id": "recsVFf42SUFrSRD3",
    "title": "Computer Problems",
    "creator": "xkcd",
    "url": "https://imgs.xkcd.com/comics/computer_problems.png",
    "tags": [
      "technology"
    ]
  },
  {
    "id": "recsccIQkPZrNxZ57",
    "title": "Seeking Answer",
    "creator": "MonkeyUser",
    "url": "https://www.monkeyuser.com/assets/images/2017/50-seeking-answer.png",
    "tags": [
      "development"
    ]
  },
  {
    "id": "rectMFfbRKyjvvaUv",
    "title": "I'm American",
    "creator": "Things in Squares",
    "url": "https://www.thingsinsquares.com/wp-content/uploads/im-an-american-comic.jpg",
    "tags": [
      "politics"
    ]
  },
  {
    "id": "rectTGV2Ib1ymsCnI",
    "title": "Lemons",
    "creator": "Things in Squares",
    "url": "https://www.thingsinsquares.com/wp-content/uploads/lemons-comic2.png",
    "tags": [
      "life"
    ]
  },
  {
    "id": "rectZImka0MZ79oFV",
    "title": "Trap III: Peace",
    "creator": "Poorly Drawn Lines",
    "url": "https://poorlydrawnlines.com/wp-content/uploads/2018/02/trap-iii-peace.png",
    "tags": [
      "animals"
    ]
  },
  {
    "id": "rectrqMlSlnbazTfq",
    "title": "Tech Support Cheat Sheet",
    "creator": "xkcd",
    "url": "https://imgs.xkcd.com/comics/tech_support_cheat_sheet.png",
    "tags": [
      "technology"
    ]
  },
  {
    "id": "recturx1ChrU0ylaC",
    "title": "Real Programmers",
    "creator": "xkcd",
    "url": "https://imgs.xkcd.com/comics/real_programmers.png",
    "tags": [
      "development"
    ]
  },
  {
    "id": "recuGDJtVlGQmarFJ",
    "title": "Process",
    "creator": "Saturday Morning Breakfast Cereal",
    "url": "https://www.smbc-comics.com/comics/1518895446-20180217.png",
    "tags": [
      "art",
      "fantasy"
    ]
  },
  {
    "id": "recvi8uM95tvwnBFy",
    "title": "Die",
    "creator": "Saturday Morning Breakfast Cereal",
    "url": "https://www.smbc-comics.com/comics/1580484842-20200131.png",
    "tags": [
      "life"
    ]
  },
  {
    "id": "recxBCw5qx9y70hIL",
    "title": "The Birds",
    "creator": "Port Sherry",
    "url": "http://portsherry.com/wp-content/uploads/2018/07/sherry609.png",
    "tags": [
      "film"
    ]
  },
  {
    "id": "recyFXnlck5QOhrD0",
    "title": "Keep Up to Date",
    "creator": "MonkeyUser",
    "url": "https://www.monkeyuser.com/assets/images/2017/49-keep-up-to-date.png",
    "tags": [
      "development"
    ]
  },
  {
    "id": "recybX436wUfs9QMR",
    "title": "Trivial Bug",
    "creator": "MonkeyUser",
    "url": "https://www.monkeyuser.com/assets/images/2017/36-trivial-bug.png",
    "tags": [
      "development"
    ]
  }
]